hot_redis/__init__.py
hot_redis/client.py
hot_redis/tests.py
hot_redis/types.py
hot_redis/lua/atoms.lua
hot_redis/lua/bit.lua
hot_redis-0.3.dist-info/DESCRIPTION.rst
hot_redis-0.3.dist-info/METADATA
hot_redis-0.3.dist-info/pydist.json
hot_redis-0.3.dist-info/RECORD
hot_redis-0.3.dist-info/top_level.txt
hot_redis-0.3.dist-info/WHEEL
