Metadata-Version: 2.0
Name: hot-redis
Version: 0.3
Summary: Higher Order Types for Redis
Home-page: http://github.com/stephenmcd/hot-redis
Author: Stephen McDonald
Author-email: steve@jupo.org
License: BSD
Platform: UNKNOWN
Classifier: Development Status :: 4 - Beta
Classifier: Intended Audience :: Developers
Classifier: License :: OSI Approved :: BSD License
Classifier: Operating System :: POSIX
Classifier: Programming Language :: Python
Classifier: Topic :: System :: Distributed Computing
Classifier: Topic :: Software Development :: Object Brokering
Requires-Dist: sphinx-me
Requires-Dist: redis
